MANIFEST.in
README.rst
setup.py
graphics.py_extra.egg-info/PKG-INFO
graphics.py_extra.egg-info/SOURCES.txt
graphics.py_extra.egg-info/dependency_links.txt
graphics.py_extra.egg-info/not-zip-safe
graphics.py_extra.egg-info/requires.txt
graphics.py_extra.egg-info/top_level.txt
graphics_extra/__init__.py
graphics_extra/free_text.py
graphics_extra/rounded_rectangle.py
graphics_extra/triangle.py