Metadata-Version: 1.2
Name: graphics.py-extra
Version: 0.1.0
Summary: Extra objects for the graphics.py package
Home-page: https://github.com/yurihs/graphics_extra/
Author: yurihs
Author-email: UNKNOWN
License: MIT
Platform: UNKNOWN
Classifier: Programming Language :: Python :: 3 :: Only
Classifier: License :: OSI Approved :: MIT License
Classifier: Development Status :: 4 - Beta
Classifier: Intended Audience :: Developers
Classifier: Natural Language :: Portuguese (Brazilian)
Classifier: Topic :: Multimedia :: Graphics
Requires-Python: >=3
